cloudstack_orchestrator/__init__.py
cloudstack_orchestrator/cli.py
cloudstack_orchestrator/sdk.py
cloudstack_orchestrator/auth/__init__.py
cloudstack_orchestrator/auth/github_oauth.py
cloudstack_orchestrator/auth/keycloak_idp.py
cloudstack_orchestrator/cli/module.py
cloudstack_orchestrator/commands/argocd.py
cloudstack_orchestrator/commands/bootstrap.py
cloudstack_orchestrator/commands/branch.py
cloudstack_orchestrator/commands/doctor.py
cloudstack_orchestrator/commands/module.py
cloudstack_orchestrator/commands/secrets.py
cloudstack_orchestrator/core/__init__.py
cloudstack_orchestrator/core/config.py
cloudstack_orchestrator/core/orchestrator.py
cloudstack_orchestrator/core/secrets.py
cloudstack_orchestrator/core/terraform.py
cloudstack_orchestrator/core/validator.py
cloudstack_orchestrator/providers/__init__.py
cloudstack_orchestrator/providers/aws.py
cloudstack_orchestrator/providers/azure.py
cloudstack_orchestrator/providers/github.py
cloudstack_orchestrator/providers/local.py
cloudstack_orchestrator/utils/azure_cli.py
cloudstack_orchestrator-2.5.0.dist-info/METADATA
cloudstack_orchestrator-2.5.0.dist-info/WHEEL
cloudstack_orchestrator-2.5.0.dist-info/entry_points.txt
cloudstack_orchestrator-2.5.0.dist-info/top_level.txt
cloudstack_orchestrator-2.5.0.dist-info/RECORD
