Metadata-Version: 2.4
Name: cloudstack-orchestrator
Version: 2.5.0
Summary: CloudStack Orchestrator SDK and CLI for automated Kubernetes platform management
Author-email: CloudStack Team <dev@cloudstack.io>
License: MIT
Project-URL: Homepage, https://github.com/killerapp/cloudstack-orchestrator
Project-URL: Documentation, https://github.com/killerapp/cloudstack-orchestrator#readme
Project-URL: Repository, https://github.com/killerapp/cloudstack-orchestrator
Project-URL: Issues, https://github.com/killerapp/cloudstack-orchestrator/issues
Keywords: kubernetes,gitops,argocd,platform,orchestration
Classifier: Development Status :: 4 - Beta
Classifier: Intended Audience :: Developers
Classifier: License :: OSI Approved :: MIT License
Classifier: Programming Language :: Python :: 3
Classifier: Programming Language :: Python :: 3.11
Classifier: Programming Language :: Python :: 3.12
Classifier: Topic :: Software Development :: Libraries :: Python Modules
Classifier: Topic :: System :: Systems Administration
Requires-Python: >=3.11
Requires-Dist: typer>=0.9.0
Requires-Dist: rich>=13.7.0
Requires-Dist: boto3>=1.34.0
Requires-Dist: google-cloud-secret-manager>=2.16.0
Requires-Dist: google-cloud-container>=2.35.0
Requires-Dist: kubernetes>=29.0.0
Requires-Dist: pyyaml>=6.0.1
Requires-Dist: pydantic>=2.5.0
Requires-Dist: pygithub>=2.1.1
Requires-Dist: requests>=2.31.0
Requires-Dist: requests-oauthlib>=2.0.0
Requires-Dist: httpx>=0.28.1
Requires-Dist: bcrypt>=4.1.0
Requires-Dist: pyjwt>=2.8.0
Requires-Dist: azure-keyvault-secrets>=4.10.0
Requires-Dist: azure-identity>=1.24.0
